<?xml version="1.0" encoding="UTF-8" standalone="yes"?>
<unit xmlns="http://www.srcML.org/srcML/src" xmlns:cpp="http://www.srcML.org/srcML/cpp" xmlns:pos="http://www.srcML.org/srcML/position" revision="0.9.5" language="C++" filename="usr/info/code/cpp/LogMonitor/LogMonitor/second/download/collectd/gumtree/collectd_repos_function_619_last_repos.cpp" pos:tabs="8"><function><specifier pos:line="1" pos:column="1">static<pos:position pos:line="1" pos:column="7"/></specifier> <type><name pos:line="1" pos:column="8">jobject<pos:position pos:line="1" pos:column="15"/></name></type> <name pos:line="1" pos:column="16">ctoj_oconfig_value<pos:position pos:line="1" pos:column="34"/></name><parameter_list pos:line="1" pos:column="34">(<parameter><decl><type><name pos:line="1" pos:column="35">JNIEnv<pos:position pos:line="1" pos:column="41"/></name> <modifier pos:line="1" pos:column="42">*<pos:position pos:line="1" pos:column="43"/></modifier></type><name pos:line="1" pos:column="43">jvm_env<pos:position pos:line="1" pos:column="50"/></name></decl></parameter>, <comment type="block" pos:line="1" pos:column="52">/* {{{ */</comment>
                                  <parameter><decl><type><name pos:line="2" pos:column="35">oconfig_value_t<pos:position pos:line="2" pos:column="50"/></name></type> <name pos:line="2" pos:column="51">ocvalue<pos:position pos:line="2" pos:column="58"/></name></decl></parameter>)<pos:position pos:line="2" pos:column="59"/></parameter_list> <block pos:line="2" pos:column="60">{
  <decl_stmt><decl><type><name pos:line="3" pos:column="3">jclass<pos:position pos:line="3" pos:column="9"/></name></type> <name pos:line="3" pos:column="10">c_ocvalue<pos:position pos:line="3" pos:column="19"/></name></decl>;<pos:position pos:line="3" pos:column="20"/></decl_stmt>
  <decl_stmt><decl><type><name pos:line="4" pos:column="3">jmethodID<pos:position pos:line="4" pos:column="12"/></name></type> <name pos:line="4" pos:column="13">m_ocvalue_constructor<pos:position pos:line="4" pos:column="34"/></name></decl>;<pos:position pos:line="4" pos:column="35"/></decl_stmt>
  <decl_stmt><decl><type><name pos:line="5" pos:column="3">jobject<pos:position pos:line="5" pos:column="10"/></name></type> <name pos:line="5" pos:column="11">o_argument<pos:position pos:line="5" pos:column="21"/></name></decl>;<pos:position pos:line="5" pos:column="22"/></decl_stmt>
  <decl_stmt><decl><type><name pos:line="6" pos:column="3">jobject<pos:position pos:line="6" pos:column="10"/></name></type> <name pos:line="6" pos:column="11">o_ocvalue<pos:position pos:line="6" pos:column="20"/></name></decl>;<pos:position pos:line="6" pos:column="21"/></decl_stmt>

  <expr_stmt><expr><name pos:line="8" pos:column="3">m_ocvalue_constructor<pos:position pos:line="8" pos:column="24"/></name> <operator pos:line="8" pos:column="25">=<pos:position pos:line="8" pos:column="26"/></operator> <name pos:line="8" pos:column="27">NULL<pos:position pos:line="8" pos:column="31"/></name></expr>;<pos:position pos:line="8" pos:column="32"/></expr_stmt>
  <expr_stmt><expr><name pos:line="9" pos:column="3">o_argument<pos:position pos:line="9" pos:column="13"/></name> <operator pos:line="9" pos:column="14">=<pos:position pos:line="9" pos:column="15"/></operator> <name pos:line="9" pos:column="16">NULL<pos:position pos:line="9" pos:column="20"/></name></expr>;<pos:position pos:line="9" pos:column="21"/></expr_stmt>

  <expr_stmt><expr><name pos:line="11" pos:column="3">c_ocvalue<pos:position pos:line="11" pos:column="12"/></name> <operator pos:line="11" pos:column="13">=<pos:position pos:line="11" pos:column="14"/></operator> <call><name><operator pos:line="11" pos:column="15">(<pos:position pos:line="11" pos:column="16"/></operator><operator pos:line="11" pos:column="16">*<pos:position pos:line="11" pos:column="17"/></operator><name pos:line="11" pos:column="17">jvm_env<pos:position pos:line="11" pos:column="24"/></name><operator pos:line="11" pos:column="24">)<pos:position pos:line="11" pos:column="25"/></operator><operator pos:line="11" pos:column="25">-&gt;<pos:position pos:line="11" pos:column="30"/></operator><name pos:line="11" pos:column="27">FindClass<pos:position pos:line="11" pos:column="36"/></name></name><argument_list pos:line="11" pos:column="36">(<argument><expr><name pos:line="11" pos:column="37">jvm_env<pos:position pos:line="11" pos:column="44"/></name></expr></argument>, <argument><expr><literal type="string" pos:line="11" pos:column="46">"org/collectd/api/OConfigValue"<pos:position pos:line="11" pos:column="77"/></literal></expr></argument>)<pos:position pos:line="11" pos:column="78"/></argument_list></call></expr>;<pos:position pos:line="11" pos:column="79"/></expr_stmt>
  <if pos:line="12" pos:column="3">if <condition pos:line="12" pos:column="6">(<expr><name pos:line="12" pos:column="7">c_ocvalue<pos:position pos:line="12" pos:column="16"/></name> <operator pos:line="12" pos:column="17">==<pos:position pos:line="12" pos:column="19"/></operator> <name pos:line="12" pos:column="20">NULL<pos:position pos:line="12" pos:column="24"/></name></expr>)<pos:position pos:line="12" pos:column="25"/></condition><then pos:line="12" pos:column="25"> <block pos:line="12" pos:column="26">{
    <expr_stmt><expr><call><name pos:line="13" pos:column="5">ERROR<pos:position pos:line="13" pos:column="10"/></name><argument_list pos:line="13" pos:column="10">(<argument><expr><literal type="string" pos:line="13" pos:column="11">"java plugin: ctoj_oconfig_value: "<pos:position pos:line="13" pos:column="46"/></literal>
          <literal type="string" pos:line="14" pos:column="11">"FindClass (org/collectd/api/OConfigValue) failed."<pos:position pos:line="14" pos:column="62"/></literal></expr></argument>)<pos:position pos:line="14" pos:column="63"/></argument_list></call></expr>;<pos:position pos:line="14" pos:column="64"/></expr_stmt>
    <return pos:line="15" pos:column="5">return <expr><name pos:line="15" pos:column="12">NULL<pos:position pos:line="15" pos:column="16"/></name></expr>;<pos:position pos:line="15" pos:column="17"/></return>
  }<pos:position pos:line="16" pos:column="4"/></block></then></if>

  <if pos:line="18" pos:column="3">if <condition pos:line="18" pos:column="6">(<expr><name><name pos:line="18" pos:column="7">ocvalue<pos:position pos:line="18" pos:column="14"/></name><operator pos:line="18" pos:column="14">.<pos:position pos:line="18" pos:column="15"/></operator><name pos:line="18" pos:column="15">type<pos:position pos:line="18" pos:column="19"/></name></name> <operator pos:line="18" pos:column="20">==<pos:position pos:line="18" pos:column="22"/></operator> <name pos:line="18" pos:column="23">OCONFIG_TYPE_BOOLEAN<pos:position pos:line="18" pos:column="43"/></name></expr>)<pos:position pos:line="18" pos:column="44"/></condition><then pos:line="18" pos:column="44"> <block pos:line="18" pos:column="45">{
    <decl_stmt><decl><type><name pos:line="19" pos:column="5">jboolean<pos:position pos:line="19" pos:column="13"/></name></type> <name pos:line="19" pos:column="14">tmp_boolean<pos:position pos:line="19" pos:column="25"/></name></decl>;<pos:position pos:line="19" pos:column="26"/></decl_stmt>

    <expr_stmt><expr><name pos:line="21" pos:column="5">tmp_boolean<pos:position pos:line="21" pos:column="16"/></name> <operator pos:line="21" pos:column="17">=<pos:position pos:line="21" pos:column="18"/></operator> <ternary><condition><expr><operator pos:line="21" pos:column="19">(<pos:position pos:line="21" pos:column="20"/></operator><name><name pos:line="21" pos:column="20">ocvalue<pos:position pos:line="21" pos:column="27"/></name><operator pos:line="21" pos:column="27">.<pos:position pos:line="21" pos:column="28"/></operator><name pos:line="21" pos:column="28">value<pos:position pos:line="21" pos:column="33"/></name><operator pos:line="21" pos:column="33">.<pos:position pos:line="21" pos:column="34"/></operator><name pos:line="21" pos:column="34">boolean<pos:position pos:line="21" pos:column="41"/></name></name> <operator pos:line="21" pos:column="42">==<pos:position pos:line="21" pos:column="44"/></operator> <literal type="number" pos:line="21" pos:column="45">0<pos:position pos:line="21" pos:column="46"/></literal><operator pos:line="21" pos:column="46">)<pos:position pos:line="21" pos:column="47"/></operator></expr> ?<pos:position pos:line="21" pos:column="49"/></condition><then pos:line="21" pos:column="49"> <expr><name pos:line="21" pos:column="50">JNI_FALSE<pos:position pos:line="21" pos:column="59"/></name></expr> <pos:position pos:line="21" pos:column="60"/></then><else pos:line="21" pos:column="60">: <expr><name pos:line="21" pos:column="62">JNI_TRUE<pos:position pos:line="21" pos:column="70"/></name></expr></else></ternary></expr>;<pos:position pos:line="21" pos:column="71"/></expr_stmt>

    <expr_stmt><expr><name pos:line="23" pos:column="5">m_ocvalue_constructor<pos:position pos:line="23" pos:column="26"/></name> <operator pos:line="23" pos:column="27">=<pos:position pos:line="23" pos:column="28"/></operator>
        <call><name><operator pos:line="24" pos:column="9">(<pos:position pos:line="24" pos:column="10"/></operator><operator pos:line="24" pos:column="10">*<pos:position pos:line="24" pos:column="11"/></operator><name pos:line="24" pos:column="11">jvm_env<pos:position pos:line="24" pos:column="18"/></name><operator pos:line="24" pos:column="18">)<pos:position pos:line="24" pos:column="19"/></operator><operator pos:line="24" pos:column="19">-&gt;<pos:position pos:line="24" pos:column="24"/></operator><name pos:line="24" pos:column="21">GetMethodID<pos:position pos:line="24" pos:column="32"/></name></name><argument_list pos:line="24" pos:column="32">(<argument><expr><name pos:line="24" pos:column="33">jvm_env<pos:position pos:line="24" pos:column="40"/></name></expr></argument>, <argument><expr><name pos:line="24" pos:column="42">c_ocvalue<pos:position pos:line="24" pos:column="51"/></name></expr></argument>, <argument><expr><literal type="string" pos:line="24" pos:column="53">"&lt;init&gt;"<pos:position pos:line="24" pos:column="67"/></literal></expr></argument>, <argument><expr><literal type="string" pos:line="24" pos:column="63">"(Z)V"<pos:position pos:line="24" pos:column="69"/></literal></expr></argument>)<pos:position pos:line="24" pos:column="70"/></argument_list></call></expr>;<pos:position pos:line="24" pos:column="71"/></expr_stmt>
    <if pos:line="25" pos:column="5">if <condition pos:line="25" pos:column="8">(<expr><name pos:line="25" pos:column="9">m_ocvalue_constructor<pos:position pos:line="25" pos:column="30"/></name> <operator pos:line="25" pos:column="31">==<pos:position pos:line="25" pos:column="33"/></operator> <name pos:line="25" pos:column="34">NULL<pos:position pos:line="25" pos:column="38"/></name></expr>)<pos:position pos:line="25" pos:column="39"/></condition><then pos:line="25" pos:column="39"> <block pos:line="25" pos:column="40">{
      <expr_stmt><expr><call><name pos:line="26" pos:column="7">ERROR<pos:position pos:line="26" pos:column="12"/></name><argument_list pos:line="26" pos:column="12">(<argument><expr><literal type="string" pos:line="26" pos:column="13">"java plugin: ctoj_oconfig_value: Cannot find the "<pos:position pos:line="26" pos:column="64"/></literal>
            <literal type="string" pos:line="27" pos:column="13">"`OConfigValue (boolean)' constructor."<pos:position pos:line="27" pos:column="52"/></literal></expr></argument>)<pos:position pos:line="27" pos:column="53"/></argument_list></call></expr>;<pos:position pos:line="27" pos:column="54"/></expr_stmt>
      <return pos:line="28" pos:column="7">return <expr><name pos:line="28" pos:column="14">NULL<pos:position pos:line="28" pos:column="18"/></name></expr>;<pos:position pos:line="28" pos:column="19"/></return>
    }<pos:position pos:line="29" pos:column="6"/></block></then></if>

    <return pos:line="31" pos:column="5">return <expr><call><name><operator pos:line="31" pos:column="12">(<pos:position pos:line="31" pos:column="13"/></operator><operator pos:line="31" pos:column="13">*<pos:position pos:line="31" pos:column="14"/></operator><name pos:line="31" pos:column="14">jvm_env<pos:position pos:line="31" pos:column="21"/></name><operator pos:line="31" pos:column="21">)<pos:position pos:line="31" pos:column="22"/></operator><operator pos:line="31" pos:column="22">-&gt;<pos:position pos:line="31" pos:column="27"/></operator><name pos:line="31" pos:column="24">NewObject<pos:position pos:line="31" pos:column="33"/></name></name><argument_list pos:line="31" pos:column="33">(<argument><expr><name pos:line="31" pos:column="34">jvm_env<pos:position pos:line="31" pos:column="41"/></name></expr></argument>, <argument><expr><name pos:line="31" pos:column="43">c_ocvalue<pos:position pos:line="31" pos:column="52"/></name></expr></argument>, <argument><expr><name pos:line="31" pos:column="54">m_ocvalue_constructor<pos:position pos:line="31" pos:column="75"/></name></expr></argument>,
                                 <argument><expr><name pos:line="32" pos:column="34">tmp_boolean<pos:position pos:line="32" pos:column="45"/></name></expr></argument>)<pos:position pos:line="32" pos:column="46"/></argument_list></call></expr>;<pos:position pos:line="32" pos:column="47"/></return>
  }<pos:position pos:line="33" pos:column="4"/></block></then> <comment type="block" pos:line="33" pos:column="5">/* if (ocvalue.type == OCONFIG_TYPE_BOOLEAN) */</comment>
  <elseif pos:line="34" pos:column="3">else <if pos:line="34" pos:column="8">if <condition pos:line="34" pos:column="11">(<expr><name><name pos:line="34" pos:column="12">ocvalue<pos:position pos:line="34" pos:column="19"/></name><operator pos:line="34" pos:column="19">.<pos:position pos:line="34" pos:column="20"/></operator><name pos:line="34" pos:column="20">type<pos:position pos:line="34" pos:column="24"/></name></name> <operator pos:line="34" pos:column="25">==<pos:position pos:line="34" pos:column="27"/></operator> <name pos:line="34" pos:column="28">OCONFIG_TYPE_STRING<pos:position pos:line="34" pos:column="47"/></name></expr>)<pos:position pos:line="34" pos:column="48"/></condition><then pos:line="34" pos:column="48"> <block pos:line="34" pos:column="49">{
    <expr_stmt><expr><name pos:line="35" pos:column="5">m_ocvalue_constructor<pos:position pos:line="35" pos:column="26"/></name> <operator pos:line="35" pos:column="27">=<pos:position pos:line="35" pos:column="28"/></operator> <call><name><operator pos:line="35" pos:column="29">(<pos:position pos:line="35" pos:column="30"/></operator><operator pos:line="35" pos:column="30">*<pos:position pos:line="35" pos:column="31"/></operator><name pos:line="35" pos:column="31">jvm_env<pos:position pos:line="35" pos:column="38"/></name><operator pos:line="35" pos:column="38">)<pos:position pos:line="35" pos:column="39"/></operator><operator pos:line="35" pos:column="39">-&gt;<pos:position pos:line="35" pos:column="44"/></operator><name pos:line="35" pos:column="41">GetMethodID<pos:position pos:line="35" pos:column="52"/></name></name><argument_list pos:line="35" pos:column="52">(
        <argument><expr><name pos:line="36" pos:column="9">jvm_env<pos:position pos:line="36" pos:column="16"/></name></expr></argument>, <argument><expr><name pos:line="36" pos:column="18">c_ocvalue<pos:position pos:line="36" pos:column="27"/></name></expr></argument>, <argument><expr><literal type="string" pos:line="36" pos:column="29">"&lt;init&gt;"<pos:position pos:line="36" pos:column="43"/></literal></expr></argument>, <argument><expr><literal type="string" pos:line="36" pos:column="39">"(Ljava/lang/String;)V"<pos:position pos:line="36" pos:column="62"/></literal></expr></argument>)<pos:position pos:line="36" pos:column="63"/></argument_list></call></expr>;<pos:position pos:line="36" pos:column="64"/></expr_stmt>
    <if pos:line="37" pos:column="5">if <condition pos:line="37" pos:column="8">(<expr><name pos:line="37" pos:column="9">m_ocvalue_constructor<pos:position pos:line="37" pos:column="30"/></name> <operator pos:line="37" pos:column="31">==<pos:position pos:line="37" pos:column="33"/></operator> <name pos:line="37" pos:column="34">NULL<pos:position pos:line="37" pos:column="38"/></name></expr>)<pos:position pos:line="37" pos:column="39"/></condition><then pos:line="37" pos:column="39"> <block pos:line="37" pos:column="40">{
      <expr_stmt><expr><call><name pos:line="38" pos:column="7">ERROR<pos:position pos:line="38" pos:column="12"/></name><argument_list pos:line="38" pos:column="12">(<argument><expr><literal type="string" pos:line="38" pos:column="13">"java plugin: ctoj_oconfig_value: Cannot find the "<pos:position pos:line="38" pos:column="64"/></literal>
            <literal type="string" pos:line="39" pos:column="13">"`OConfigValue (String)' constructor."<pos:position pos:line="39" pos:column="51"/></literal></expr></argument>)<pos:position pos:line="39" pos:column="52"/></argument_list></call></expr>;<pos:position pos:line="39" pos:column="53"/></expr_stmt>
      <return pos:line="40" pos:column="7">return <expr><name pos:line="40" pos:column="14">NULL<pos:position pos:line="40" pos:column="18"/></name></expr>;<pos:position pos:line="40" pos:column="19"/></return>
    }<pos:position pos:line="41" pos:column="6"/></block></then></if>

    <expr_stmt><expr><name pos:line="43" pos:column="5">o_argument<pos:position pos:line="43" pos:column="15"/></name> <operator pos:line="43" pos:column="16">=<pos:position pos:line="43" pos:column="17"/></operator> <call><name><operator pos:line="43" pos:column="18">(<pos:position pos:line="43" pos:column="19"/></operator><operator pos:line="43" pos:column="19">*<pos:position pos:line="43" pos:column="20"/></operator><name pos:line="43" pos:column="20">jvm_env<pos:position pos:line="43" pos:column="27"/></name><operator pos:line="43" pos:column="27">)<pos:position pos:line="43" pos:column="28"/></operator><operator pos:line="43" pos:column="28">-&gt;<pos:position pos:line="43" pos:column="33"/></operator><name pos:line="43" pos:column="30">NewStringUTF<pos:position pos:line="43" pos:column="42"/></name></name><argument_list pos:line="43" pos:column="42">(<argument><expr><name pos:line="43" pos:column="43">jvm_env<pos:position pos:line="43" pos:column="50"/></name></expr></argument>, <argument><expr><name><name pos:line="43" pos:column="52">ocvalue<pos:position pos:line="43" pos:column="59"/></name><operator pos:line="43" pos:column="59">.<pos:position pos:line="43" pos:column="60"/></operator><name pos:line="43" pos:column="60">value<pos:position pos:line="43" pos:column="65"/></name><operator pos:line="43" pos:column="65">.<pos:position pos:line="43" pos:column="66"/></operator><name pos:line="43" pos:column="66">string<pos:position pos:line="43" pos:column="72"/></name></name></expr></argument>)<pos:position pos:line="43" pos:column="73"/></argument_list></call></expr>;<pos:position pos:line="43" pos:column="74"/></expr_stmt>
    <if pos:line="44" pos:column="5">if <condition pos:line="44" pos:column="8">(<expr><name pos:line="44" pos:column="9">o_argument<pos:position pos:line="44" pos:column="19"/></name> <operator pos:line="44" pos:column="20">==<pos:position pos:line="44" pos:column="22"/></operator> <name pos:line="44" pos:column="23">NULL<pos:position pos:line="44" pos:column="27"/></name></expr>)<pos:position pos:line="44" pos:column="28"/></condition><then pos:line="44" pos:column="28"> <block pos:line="44" pos:column="29">{
      <expr_stmt><expr><call><name pos:line="45" pos:column="7">ERROR<pos:position pos:line="45" pos:column="12"/></name><argument_list pos:line="45" pos:column="12">(<argument><expr><literal type="string" pos:line="45" pos:column="13">"java plugin: ctoj_oconfig_value: "<pos:position pos:line="45" pos:column="48"/></literal>
            <literal type="string" pos:line="46" pos:column="13">"Creating a String object failed."<pos:position pos:line="46" pos:column="47"/></literal></expr></argument>)<pos:position pos:line="46" pos:column="48"/></argument_list></call></expr>;<pos:position pos:line="46" pos:column="49"/></expr_stmt>
      <return pos:line="47" pos:column="7">return <expr><name pos:line="47" pos:column="14">NULL<pos:position pos:line="47" pos:column="18"/></name></expr>;<pos:position pos:line="47" pos:column="19"/></return>
    }<pos:position pos:line="48" pos:column="6"/></block></then></if>
  }<pos:position pos:line="49" pos:column="4"/></block></then></if></elseif> <elseif pos:line="49" pos:column="5">else <if pos:line="49" pos:column="10">if <condition pos:line="49" pos:column="13">(<expr><name><name pos:line="49" pos:column="14">ocvalue<pos:position pos:line="49" pos:column="21"/></name><operator pos:line="49" pos:column="21">.<pos:position pos:line="49" pos:column="22"/></operator><name pos:line="49" pos:column="22">type<pos:position pos:line="49" pos:column="26"/></name></name> <operator pos:line="49" pos:column="27">==<pos:position pos:line="49" pos:column="29"/></operator> <name pos:line="49" pos:column="30">OCONFIG_TYPE_NUMBER<pos:position pos:line="49" pos:column="49"/></name></expr>)<pos:position pos:line="49" pos:column="50"/></condition><then pos:line="49" pos:column="50"> <block pos:line="49" pos:column="51">{
    <expr_stmt><expr><name pos:line="50" pos:column="5">m_ocvalue_constructor<pos:position pos:line="50" pos:column="26"/></name> <operator pos:line="50" pos:column="27">=<pos:position pos:line="50" pos:column="28"/></operator> <call><name><operator pos:line="50" pos:column="29">(<pos:position pos:line="50" pos:column="30"/></operator><operator pos:line="50" pos:column="30">*<pos:position pos:line="50" pos:column="31"/></operator><name pos:line="50" pos:column="31">jvm_env<pos:position pos:line="50" pos:column="38"/></name><operator pos:line="50" pos:column="38">)<pos:position pos:line="50" pos:column="39"/></operator><operator pos:line="50" pos:column="39">-&gt;<pos:position pos:line="50" pos:column="44"/></operator><name pos:line="50" pos:column="41">GetMethodID<pos:position pos:line="50" pos:column="52"/></name></name><argument_list pos:line="50" pos:column="52">(
        <argument><expr><name pos:line="51" pos:column="9">jvm_env<pos:position pos:line="51" pos:column="16"/></name></expr></argument>, <argument><expr><name pos:line="51" pos:column="18">c_ocvalue<pos:position pos:line="51" pos:column="27"/></name></expr></argument>, <argument><expr><literal type="string" pos:line="51" pos:column="29">"&lt;init&gt;"<pos:position pos:line="51" pos:column="43"/></literal></expr></argument>, <argument><expr><literal type="string" pos:line="51" pos:column="39">"(Ljava/lang/Number;)V"<pos:position pos:line="51" pos:column="62"/></literal></expr></argument>)<pos:position pos:line="51" pos:column="63"/></argument_list></call></expr>;<pos:position pos:line="51" pos:column="64"/></expr_stmt>
    <if pos:line="52" pos:column="5">if <condition pos:line="52" pos:column="8">(<expr><name pos:line="52" pos:column="9">m_ocvalue_constructor<pos:position pos:line="52" pos:column="30"/></name> <operator pos:line="52" pos:column="31">==<pos:position pos:line="52" pos:column="33"/></operator> <name pos:line="52" pos:column="34">NULL<pos:position pos:line="52" pos:column="38"/></name></expr>)<pos:position pos:line="52" pos:column="39"/></condition><then pos:line="52" pos:column="39"> <block pos:line="52" pos:column="40">{
      <expr_stmt><expr><call><name pos:line="53" pos:column="7">ERROR<pos:position pos:line="53" pos:column="12"/></name><argument_list pos:line="53" pos:column="12">(<argument><expr><literal type="string" pos:line="53" pos:column="13">"java plugin: ctoj_oconfig_value: Cannot find the "<pos:position pos:line="53" pos:column="64"/></literal>
            <literal type="string" pos:line="54" pos:column="13">"`OConfigValue (Number)' constructor."<pos:position pos:line="54" pos:column="51"/></literal></expr></argument>)<pos:position pos:line="54" pos:column="52"/></argument_list></call></expr>;<pos:position pos:line="54" pos:column="53"/></expr_stmt>
      <return pos:line="55" pos:column="7">return <expr><name pos:line="55" pos:column="14">NULL<pos:position pos:line="55" pos:column="18"/></name></expr>;<pos:position pos:line="55" pos:column="19"/></return>
    }<pos:position pos:line="56" pos:column="6"/></block></then></if>

    <expr_stmt><expr><name pos:line="58" pos:column="5">o_argument<pos:position pos:line="58" pos:column="15"/></name> <operator pos:line="58" pos:column="16">=<pos:position pos:line="58" pos:column="17"/></operator> <call><name pos:line="58" pos:column="18">ctoj_jdouble_to_number<pos:position pos:line="58" pos:column="40"/></name><argument_list pos:line="58" pos:column="40">(<argument><expr><name pos:line="58" pos:column="41">jvm_env<pos:position pos:line="58" pos:column="48"/></name></expr></argument>, <argument><expr><operator pos:line="58" pos:column="50">(<pos:position pos:line="58" pos:column="51"/></operator><name pos:line="58" pos:column="51">jdouble<pos:position pos:line="58" pos:column="58"/></name><operator pos:line="58" pos:column="58">)<pos:position pos:line="58" pos:column="59"/></operator><name><name pos:line="58" pos:column="59">ocvalue<pos:position pos:line="58" pos:column="66"/></name><operator pos:line="58" pos:column="66">.<pos:position pos:line="58" pos:column="67"/></operator><name pos:line="58" pos:column="67">value<pos:position pos:line="58" pos:column="72"/></name><operator pos:line="58" pos:column="72">.<pos:position pos:line="58" pos:column="73"/></operator><name pos:line="58" pos:column="73">number<pos:position pos:line="58" pos:column="79"/></name></name></expr></argument>)<pos:position pos:line="58" pos:column="80"/></argument_list></call></expr>;<pos:position pos:line="58" pos:column="81"/></expr_stmt>
    <if pos:line="59" pos:column="5">if <condition pos:line="59" pos:column="8">(<expr><name pos:line="59" pos:column="9">o_argument<pos:position pos:line="59" pos:column="19"/></name> <operator pos:line="59" pos:column="20">==<pos:position pos:line="59" pos:column="22"/></operator> <name pos:line="59" pos:column="23">NULL<pos:position pos:line="59" pos:column="27"/></name></expr>)<pos:position pos:line="59" pos:column="28"/></condition><then pos:line="59" pos:column="28"> <block pos:line="59" pos:column="29">{
      <expr_stmt><expr><call><name pos:line="60" pos:column="7">ERROR<pos:position pos:line="60" pos:column="12"/></name><argument_list pos:line="60" pos:column="12">(<argument><expr><literal type="string" pos:line="60" pos:column="13">"java plugin: ctoj_oconfig_value: "<pos:position pos:line="60" pos:column="48"/></literal>
            <literal type="string" pos:line="61" pos:column="13">"Creating a Number object failed."<pos:position pos:line="61" pos:column="47"/></literal></expr></argument>)<pos:position pos:line="61" pos:column="48"/></argument_list></call></expr>;<pos:position pos:line="61" pos:column="49"/></expr_stmt>
      <return pos:line="62" pos:column="7">return <expr><name pos:line="62" pos:column="14">NULL<pos:position pos:line="62" pos:column="18"/></name></expr>;<pos:position pos:line="62" pos:column="19"/></return>
    }<pos:position pos:line="63" pos:column="6"/></block></then></if>
  }<pos:position pos:line="64" pos:column="4"/></block></then></if></elseif> <else pos:line="64" pos:column="5">else <block pos:line="64" pos:column="10">{
    <return pos:line="65" pos:column="5">return <expr><name pos:line="65" pos:column="12">NULL<pos:position pos:line="65" pos:column="16"/></name></expr>;<pos:position pos:line="65" pos:column="17"/></return>
  }<pos:position pos:line="66" pos:column="4"/></block></else></if>

  <expr_stmt><expr><call><name pos:line="68" pos:column="3">assert<pos:position pos:line="68" pos:column="9"/></name><argument_list pos:line="68" pos:column="9">(<argument><expr><name pos:line="68" pos:column="10">m_ocvalue_constructor<pos:position pos:line="68" pos:column="31"/></name> <operator pos:line="68" pos:column="32">!=<pos:position pos:line="68" pos:column="34"/></operator> <name pos:line="68" pos:column="35">NULL<pos:position pos:line="68" pos:column="39"/></name></expr></argument>)<pos:position pos:line="68" pos:column="40"/></argument_list></call></expr>;<pos:position pos:line="68" pos:column="41"/></expr_stmt>
  <expr_stmt><expr><call><name pos:line="69" pos:column="3">assert<pos:position pos:line="69" pos:column="9"/></name><argument_list pos:line="69" pos:column="9">(<argument><expr><name pos:line="69" pos:column="10">o_argument<pos:position pos:line="69" pos:column="20"/></name> <operator pos:line="69" pos:column="21">!=<pos:position pos:line="69" pos:column="23"/></operator> <name pos:line="69" pos:column="24">NULL<pos:position pos:line="69" pos:column="28"/></name></expr></argument>)<pos:position pos:line="69" pos:column="29"/></argument_list></call></expr>;<pos:position pos:line="69" pos:column="30"/></expr_stmt>

  <expr_stmt><expr><name pos:line="71" pos:column="3">o_ocvalue<pos:position pos:line="71" pos:column="12"/></name> <operator pos:line="71" pos:column="13">=<pos:position pos:line="71" pos:column="14"/></operator> <call><name><operator pos:line="71" pos:column="15">(<pos:position pos:line="71" pos:column="16"/></operator><operator pos:line="71" pos:column="16">*<pos:position pos:line="71" pos:column="17"/></operator><name pos:line="71" pos:column="17">jvm_env<pos:position pos:line="71" pos:column="24"/></name><operator pos:line="71" pos:column="24">)<pos:position pos:line="71" pos:column="25"/></operator><operator pos:line="71" pos:column="25">-&gt;<pos:position pos:line="71" pos:column="30"/></operator><name pos:line="71" pos:column="27">NewObject<pos:position pos:line="71" pos:column="36"/></name></name><argument_list pos:line="71" pos:column="36">(<argument><expr><name pos:line="71" pos:column="37">jvm_env<pos:position pos:line="71" pos:column="44"/></name></expr></argument>, <argument><expr><name pos:line="71" pos:column="46">c_ocvalue<pos:position pos:line="71" pos:column="55"/></name></expr></argument>, <argument><expr><name pos:line="71" pos:column="57">m_ocvalue_constructor<pos:position pos:line="71" pos:column="78"/></name></expr></argument>,
                                    <argument><expr><name pos:line="72" pos:column="37">o_argument<pos:position pos:line="72" pos:column="47"/></name></expr></argument>)<pos:position pos:line="72" pos:column="48"/></argument_list></call></expr>;<pos:position pos:line="72" pos:column="49"/></expr_stmt>
  <if pos:line="73" pos:column="3">if <condition pos:line="73" pos:column="6">(<expr><name pos:line="73" pos:column="7">o_ocvalue<pos:position pos:line="73" pos:column="16"/></name> <operator pos:line="73" pos:column="17">==<pos:position pos:line="73" pos:column="19"/></operator> <name pos:line="73" pos:column="20">NULL<pos:position pos:line="73" pos:column="24"/></name></expr>)<pos:position pos:line="73" pos:column="25"/></condition><then pos:line="73" pos:column="25"> <block pos:line="73" pos:column="26">{
    <expr_stmt><expr><call><name pos:line="74" pos:column="5">ERROR<pos:position pos:line="74" pos:column="10"/></name><argument_list pos:line="74" pos:column="10">(<argument><expr><literal type="string" pos:line="74" pos:column="11">"java plugin: ctoj_oconfig_value: "<pos:position pos:line="74" pos:column="46"/></literal>
          <literal type="string" pos:line="75" pos:column="11">"Creating an OConfigValue object failed."<pos:position pos:line="75" pos:column="52"/></literal></expr></argument>)<pos:position pos:line="75" pos:column="53"/></argument_list></call></expr>;<pos:position pos:line="75" pos:column="54"/></expr_stmt>
    <expr_stmt><expr><call><name><operator pos:line="76" pos:column="5">(<pos:position pos:line="76" pos:column="6"/></operator><operator pos:line="76" pos:column="6">*<pos:position pos:line="76" pos:column="7"/></operator><name pos:line="76" pos:column="7">jvm_env<pos:position pos:line="76" pos:column="14"/></name><operator pos:line="76" pos:column="14">)<pos:position pos:line="76" pos:column="15"/></operator><operator pos:line="76" pos:column="15">-&gt;<pos:position pos:line="76" pos:column="20"/></operator><name pos:line="76" pos:column="17">DeleteLocalRef<pos:position pos:line="76" pos:column="31"/></name></name><argument_list pos:line="76" pos:column="31">(<argument><expr><name pos:line="76" pos:column="32">jvm_env<pos:position pos:line="76" pos:column="39"/></name></expr></argument>, <argument><expr><name pos:line="76" pos:column="41">o_argument<pos:position pos:line="76" pos:column="51"/></name></expr></argument>)<pos:position pos:line="76" pos:column="52"/></argument_list></call></expr>;<pos:position pos:line="76" pos:column="53"/></expr_stmt>
    <return pos:line="77" pos:column="5">return <expr><name pos:line="77" pos:column="12">NULL<pos:position pos:line="77" pos:column="16"/></name></expr>;<pos:position pos:line="77" pos:column="17"/></return>
  }<pos:position pos:line="78" pos:column="4"/></block></then></if>

  <expr_stmt><expr><call><name><operator pos:line="80" pos:column="3">(<pos:position pos:line="80" pos:column="4"/></operator><operator pos:line="80" pos:column="4">*<pos:position pos:line="80" pos:column="5"/></operator><name pos:line="80" pos:column="5">jvm_env<pos:position pos:line="80" pos:column="12"/></name><operator pos:line="80" pos:column="12">)<pos:position pos:line="80" pos:column="13"/></operator><operator pos:line="80" pos:column="13">-&gt;<pos:position pos:line="80" pos:column="18"/></operator><name pos:line="80" pos:column="15">DeleteLocalRef<pos:position pos:line="80" pos:column="29"/></name></name><argument_list pos:line="80" pos:column="29">(<argument><expr><name pos:line="80" pos:column="30">jvm_env<pos:position pos:line="80" pos:column="37"/></name></expr></argument>, <argument><expr><name pos:line="80" pos:column="39">o_argument<pos:position pos:line="80" pos:column="49"/></name></expr></argument>)<pos:position pos:line="80" pos:column="50"/></argument_list></call></expr>;<pos:position pos:line="80" pos:column="51"/></expr_stmt>
  <return pos:line="81" pos:column="3">return <expr><name pos:line="81" pos:column="10">o_ocvalue<pos:position pos:line="81" pos:column="19"/></name></expr>;<pos:position pos:line="81" pos:column="20"/></return>
}<pos:position pos:line="82" pos:column="2"/></block></function></unit>
