<?xml version="1.0" encoding="UTF-8" standalone="yes"?>
<unit xmlns="http://www.srcML.org/srcML/src" xmlns:cpp="http://www.srcML.org/srcML/cpp" xmlns:pos="http://www.srcML.org/srcML/position" revision="0.9.5" language="C++" filename="usr/info/code/cpp/LogMonitor/LogMonitor/second/download/squid/gumtree/squid_repos_function_5153_squid-3.5.27.cpp" pos:tabs="8"><function><type><name pos:line="1" pos:column="1">int64_t<pos:position pos:line="1" pos:column="8"/></name></type>
<name><name pos:line="2" pos:column="1">Rock<pos:position pos:line="2" pos:column="5"/></name><operator pos:line="2" pos:column="5">::<pos:position pos:line="2" pos:column="7"/></operator><name pos:line="2" pos:column="7">SwapDir<pos:position pos:line="2" pos:column="14"/></name><operator pos:line="2" pos:column="14">::<pos:position pos:line="2" pos:column="16"/></operator><name pos:line="2" pos:column="16">diskOffsetLimit<pos:position pos:line="2" pos:column="31"/></name></name><parameter_list pos:line="2" pos:column="31">()<pos:position pos:line="2" pos:column="33"/></parameter_list> <specifier pos:line="2" pos:column="34">const<pos:position pos:line="2" pos:column="39"/></specifier>
<block pos:line="3" pos:column="1">{
    <expr_stmt><expr><call><name pos:line="4" pos:column="5">assert<pos:position pos:line="4" pos:column="11"/></name><argument_list pos:line="4" pos:column="11">(<argument><expr><name pos:line="4" pos:column="12">map<pos:position pos:line="4" pos:column="15"/></name></expr></argument>)<pos:position pos:line="4" pos:column="16"/></argument_list></call></expr>;<pos:position pos:line="4" pos:column="17"/></expr_stmt>
    <return pos:line="5" pos:column="5">return <expr><call><name pos:line="5" pos:column="12">diskOffset<pos:position pos:line="5" pos:column="22"/></name><argument_list pos:line="5" pos:column="22">(<argument><expr><call><name><name pos:line="5" pos:column="23">map<pos:position pos:line="5" pos:column="26"/></name><operator pos:line="5" pos:column="26">-&gt;<pos:position pos:line="5" pos:column="31"/></operator><name pos:line="5" pos:column="28">sliceLimit<pos:position pos:line="5" pos:column="38"/></name></name><argument_list pos:line="5" pos:column="38">()<pos:position pos:line="5" pos:column="40"/></argument_list></call></expr></argument>)<pos:position pos:line="5" pos:column="41"/></argument_list></call></expr>;<pos:position pos:line="5" pos:column="42"/></return>
}<pos:position pos:line="6" pos:column="2"/></block></function></unit>
