<?xml version="1.0" encoding="UTF-8" standalone="yes"?>
<unit xmlns="http://www.srcML.org/srcML/src" xmlns:cpp="http://www.srcML.org/srcML/cpp" xmlns:pos="http://www.srcML.org/srcML/position" revision="0.9.5" language="C++" filename="usr/info/code/cpp/LogMonitor/LogMonitor/second/download/squid/gumtree/squid_repos_function_881_squid-3.3.14.cpp" pos:tabs="8"><function><type><name pos:line="1" pos:column="1">int<pos:position pos:line="1" pos:column="4"/></name></type>
<name pos:line="2" pos:column="1">commUnsetConnTimeout<pos:position pos:line="2" pos:column="21"/></name><parameter_list pos:line="2" pos:column="21">(<parameter><decl><type><specifier pos:line="2" pos:column="22">const<pos:position pos:line="2" pos:column="27"/></specifier> <name><name pos:line="2" pos:column="28">Comm<pos:position pos:line="2" pos:column="32"/></name><operator pos:line="2" pos:column="32">::<pos:position pos:line="2" pos:column="34"/></operator><name pos:line="2" pos:column="34">ConnectionPointer<pos:position pos:line="2" pos:column="51"/></name></name> <modifier pos:line="2" pos:column="52">&amp;<pos:position pos:line="2" pos:column="57"/></modifier></type><name pos:line="2" pos:column="53">conn<pos:position pos:line="2" pos:column="57"/></name></decl></parameter>)<pos:position pos:line="2" pos:column="58"/></parameter_list>
<block pos:line="3" pos:column="1">{
    <expr_stmt><expr><call><name pos:line="4" pos:column="5">debugs<pos:position pos:line="4" pos:column="11"/></name><argument_list pos:line="4" pos:column="11">(<argument><expr><literal type="number" pos:line="4" pos:column="12">5<pos:position pos:line="4" pos:column="13"/></literal></expr></argument>, <argument><expr><literal type="number" pos:line="4" pos:column="15">3<pos:position pos:line="4" pos:column="16"/></literal></expr></argument>, <argument><expr><name pos:line="4" pos:column="18">HERE<pos:position pos:line="4" pos:column="22"/></name> <operator pos:line="4" pos:column="23">&lt;&lt;<pos:position pos:line="4" pos:column="31"/></operator> <literal type="string" pos:line="4" pos:column="26">"Remove timeout for "<pos:position pos:line="4" pos:column="47"/></literal> <operator pos:line="4" pos:column="48">&lt;&lt;<pos:position pos:line="4" pos:column="56"/></operator> <name pos:line="4" pos:column="51">conn<pos:position pos:line="4" pos:column="55"/></name></expr></argument>)<pos:position pos:line="4" pos:column="56"/></argument_list></call></expr>;<pos:position pos:line="4" pos:column="57"/></expr_stmt>
    <decl_stmt><decl><type><name><name pos:line="5" pos:column="5">AsyncCall<pos:position pos:line="5" pos:column="14"/></name><operator pos:line="5" pos:column="14">::<pos:position pos:line="5" pos:column="16"/></operator><name pos:line="5" pos:column="16">Pointer<pos:position pos:line="5" pos:column="23"/></name></name></type> <name pos:line="5" pos:column="24">nil<pos:position pos:line="5" pos:column="27"/></name></decl>;<pos:position pos:line="5" pos:column="28"/></decl_stmt>
    <return pos:line="6" pos:column="5">return <expr><call><name pos:line="6" pos:column="12">commSetConnTimeout<pos:position pos:line="6" pos:column="30"/></name><argument_list pos:line="6" pos:column="30">(<argument><expr><name pos:line="6" pos:column="31">conn<pos:position pos:line="6" pos:column="35"/></name></expr></argument>, <argument><expr><operator pos:line="6" pos:column="37">-<pos:position pos:line="6" pos:column="38"/></operator><literal type="number" pos:line="6" pos:column="38">1<pos:position pos:line="6" pos:column="39"/></literal></expr></argument>, <argument><expr><name pos:line="6" pos:column="41">nil<pos:position pos:line="6" pos:column="44"/></name></expr></argument>)<pos:position pos:line="6" pos:column="45"/></argument_list></call></expr>;<pos:position pos:line="6" pos:column="46"/></return>
}<pos:position pos:line="7" pos:column="2"/></block></function></unit>
