<?xml version="1.0" encoding="UTF-8" standalone="yes"?>
<unit xmlns="http://www.srcML.org/srcML/src" xmlns:cpp="http://www.srcML.org/srcML/cpp" xmlns:pos="http://www.srcML.org/srcML/position" revision="0.9.5" language="C++" filename="usr/info/code/cpp/LogMonitor/LogMonitor/second/download/squid/gumtree/squid_repos_function_6910_squid-3.5.27.cpp" pos:tabs="8"><function><type><specifier pos:line="1" pos:column="1">const<pos:position pos:line="1" pos:column="6"/></specifier> <name><name pos:line="1" pos:column="7">Ipc<pos:position pos:line="1" pos:column="10"/></name><operator pos:line="1" pos:column="10">::<pos:position pos:line="1" pos:column="12"/></operator><name pos:line="1" pos:column="12">OneToOneUniQueue<pos:position pos:line="1" pos:column="28"/></name></name> <modifier pos:line="1" pos:column="29">&amp;<pos:position pos:line="1" pos:column="34"/></modifier></type>
<name><name pos:line="2" pos:column="1">Ipc<pos:position pos:line="2" pos:column="4"/></name><operator pos:line="2" pos:column="4">::<pos:position pos:line="2" pos:column="6"/></operator><name pos:line="2" pos:column="6">MultiQueue<pos:position pos:line="2" pos:column="16"/></name><operator pos:line="2" pos:column="16">::<pos:position pos:line="2" pos:column="18"/></operator><name pos:line="2" pos:column="18">oneToOneQueue<pos:position pos:line="2" pos:column="31"/></name></name><parameter_list pos:line="2" pos:column="31">(<parameter><decl><type><specifier pos:line="2" pos:column="32">const<pos:position pos:line="2" pos:column="37"/></specifier> <name pos:line="2" pos:column="38">int<pos:position pos:line="2" pos:column="41"/></name></type> <name pos:line="2" pos:column="42">fromProcessId<pos:position pos:line="2" pos:column="55"/></name></decl></parameter>, <parameter><decl><type><specifier pos:line="2" pos:column="57">const<pos:position pos:line="2" pos:column="62"/></specifier> <name pos:line="2" pos:column="63">int<pos:position pos:line="2" pos:column="66"/></name></type> <name pos:line="2" pos:column="67">toProcessId<pos:position pos:line="2" pos:column="78"/></name></decl></parameter>)<pos:position pos:line="2" pos:column="79"/></parameter_list> <specifier pos:line="2" pos:column="80">const<pos:position pos:line="2" pos:column="85"/></specifier>
<block pos:line="3" pos:column="1">{
    <expr_stmt><expr><call><name pos:line="4" pos:column="5">assert<pos:position pos:line="4" pos:column="11"/></name><argument_list pos:line="4" pos:column="11">(<argument><expr><call><name pos:line="4" pos:column="12">validProcessId<pos:position pos:line="4" pos:column="26"/></name><argument_list pos:line="4" pos:column="26">(<argument><expr><name pos:line="4" pos:column="27">fromProcessId<pos:position pos:line="4" pos:column="40"/></name></expr></argument>)<pos:position pos:line="4" pos:column="41"/></argument_list></call></expr></argument>)<pos:position pos:line="4" pos:column="42"/></argument_list></call></expr>;<pos:position pos:line="4" pos:column="43"/></expr_stmt>
    <expr_stmt><expr><call><name pos:line="5" pos:column="5">assert<pos:position pos:line="5" pos:column="11"/></name><argument_list pos:line="5" pos:column="11">(<argument><expr><call><name pos:line="5" pos:column="12">validProcessId<pos:position pos:line="5" pos:column="26"/></name><argument_list pos:line="5" pos:column="26">(<argument><expr><name pos:line="5" pos:column="27">toProcessId<pos:position pos:line="5" pos:column="38"/></name></expr></argument>)<pos:position pos:line="5" pos:column="39"/></argument_list></call></expr></argument>)<pos:position pos:line="5" pos:column="40"/></argument_list></call></expr>;<pos:position pos:line="5" pos:column="41"/></expr_stmt>
    <decl_stmt><decl><type><specifier pos:line="6" pos:column="5">const<pos:position pos:line="6" pos:column="10"/></specifier> <name pos:line="6" pos:column="11">int<pos:position pos:line="6" pos:column="14"/></name></type> <name pos:line="6" pos:column="15">fromIndex<pos:position pos:line="6" pos:column="24"/></name> <init pos:line="6" pos:column="25">= <expr><name pos:line="6" pos:column="27">fromProcessId<pos:position pos:line="6" pos:column="40"/></name> <operator pos:line="6" pos:column="41">-<pos:position pos:line="6" pos:column="42"/></operator> <name><name pos:line="6" pos:column="43">metadata<pos:position pos:line="6" pos:column="51"/></name><operator pos:line="6" pos:column="51">-&gt;<pos:position pos:line="6" pos:column="56"/></operator><name pos:line="6" pos:column="53">theProcessIdOffset<pos:position pos:line="6" pos:column="71"/></name></name></expr></init></decl>;<pos:position pos:line="6" pos:column="72"/></decl_stmt>
    <decl_stmt><decl><type><specifier pos:line="7" pos:column="5">const<pos:position pos:line="7" pos:column="10"/></specifier> <name pos:line="7" pos:column="11">int<pos:position pos:line="7" pos:column="14"/></name></type> <name pos:line="7" pos:column="15">toIndex<pos:position pos:line="7" pos:column="22"/></name> <init pos:line="7" pos:column="23">= <expr><name pos:line="7" pos:column="25">toProcessId<pos:position pos:line="7" pos:column="36"/></name> <operator pos:line="7" pos:column="37">-<pos:position pos:line="7" pos:column="38"/></operator> <name><name pos:line="7" pos:column="39">metadata<pos:position pos:line="7" pos:column="47"/></name><operator pos:line="7" pos:column="47">-&gt;<pos:position pos:line="7" pos:column="52"/></operator><name pos:line="7" pos:column="49">theProcessIdOffset<pos:position pos:line="7" pos:column="67"/></name></name></expr></init></decl>;<pos:position pos:line="7" pos:column="68"/></decl_stmt>
    <decl_stmt><decl><type><specifier pos:line="8" pos:column="5">const<pos:position pos:line="8" pos:column="10"/></specifier> <name pos:line="8" pos:column="11">int<pos:position pos:line="8" pos:column="14"/></name></type> <name pos:line="8" pos:column="15">index<pos:position pos:line="8" pos:column="20"/></name> <init pos:line="8" pos:column="21">= <expr><name pos:line="8" pos:column="23">fromIndex<pos:position pos:line="8" pos:column="32"/></name> <operator pos:line="8" pos:column="33">*<pos:position pos:line="8" pos:column="34"/></operator> <name><name pos:line="8" pos:column="35">metadata<pos:position pos:line="8" pos:column="43"/></name><operator pos:line="8" pos:column="43">-&gt;<pos:position pos:line="8" pos:column="48"/></operator><name pos:line="8" pos:column="45">theProcessCount<pos:position pos:line="8" pos:column="60"/></name></name> <operator pos:line="8" pos:column="61">+<pos:position pos:line="8" pos:column="62"/></operator> <name pos:line="8" pos:column="63">toIndex<pos:position pos:line="8" pos:column="70"/></name></expr></init></decl>;<pos:position pos:line="8" pos:column="71"/></decl_stmt>
    <return pos:line="9" pos:column="5">return <expr><operator pos:line="9" pos:column="12">(<pos:position pos:line="9" pos:column="13"/></operator><operator pos:line="9" pos:column="13">*<pos:position pos:line="9" pos:column="14"/></operator><name pos:line="9" pos:column="14">queues<pos:position pos:line="9" pos:column="20"/></name><operator pos:line="9" pos:column="20">)<pos:position pos:line="9" pos:column="21"/></operator><index pos:line="9" pos:column="21">[<expr><name pos:line="9" pos:column="22">index<pos:position pos:line="9" pos:column="27"/></name></expr>]<pos:position pos:line="9" pos:column="28"/></index></expr>;<pos:position pos:line="9" pos:column="29"/></return>
}<pos:position pos:line="10" pos:column="2"/></block></function></unit>
